makey/__init__.py
makey/__main__.py
makey-0.0.15.dist-info/entry_points.txt
makey-0.0.15.dist-info/WHEEL
makey-0.0.15.dist-info/METADATA
makey-0.0.15.dist-info/RECORD
